opencerebro/__init__.py
opencerebro-0.1.7.dist-info/METADATA
opencerebro-0.1.7.dist-info/WHEEL
opencerebro-0.1.7.dist-info/RECORD
